orpheus/__init__.py
orpheus/catalog.py
orpheus/covariance.py
orpheus/direct.py
orpheus/flat2dgrid.py
orpheus/npcf_base.py
orpheus/npcf_fourth.py
orpheus/npcf_second.py
orpheus/npcf_third.py
orpheus/orpheus_clib.cpython-311-x86_64-linux-musl.so
orpheus/patchutils.py
orpheus/utils.py
orpheus_npcf.libs/libgomp-8949ffbe.so.1.0.0
orpheus_npcf-0.2.1.dist-info/METADATA
orpheus_npcf-0.2.1.dist-info/WHEEL
orpheus_npcf-0.2.1.dist-info/top_level.txt
orpheus_npcf-0.2.1.dist-info/RECORD
orpheus_npcf-0.2.1.dist-info/licenses/LICENSE
orpheus_npcf-0.2.1.dist-info/sboms/auditwheel.cdx.json
