Metadata-Version: 2.4
Name: orpheus-npcf
Version: 0.2.1
Summary: Compute N-point correlation functions of spin-s fields.
Home-page: https://github.com/lporth93/orpheus
Author: Lucas Porth
License: MIT
Classifier: Development Status :: 4 - Beta
Classifier: Programming Language :: Python :: 3
Classifier: License :: OSI Approved :: MIT License
Requires-Python: >=3.9
License-File: LICENSE
Requires-Dist: astropy>=6
Requires-Dist: healpy>=1.17
Requires-Dist: coverage>=7.6.1
Requires-Dist: numba<=0.62.1,>=0.58
Requires-Dist: numpy<1.27,>=1.22
Requires-Dist: scipy>=1.15
Requires-Dist: scikit-learn
Dynamic: author
Dynamic: classifier
Dynamic: description
Dynamic: description-content-type
Dynamic: home-page
Dynamic: license
Dynamic: license-file
Dynamic: requires-dist
Dynamic: requires-python
Dynamic: summary
